invidious/__init__.py
invidious/channel.py
invidious/channel_item.py
invidious/comment.py
invidious/comments_list.py
invidious/config.py
invidious/invidious.py
invidious/model.py
invidious/playlist_item.py
invidious/recommended_video.py
invidious/short_video.py
invidious/video.py
invidious/video_item.py
invidious/enums/__init__.py
invidious/enums/content_type.py
invidious/enums/duration.py
invidious/enums/feauter.py
invidious/enums/iv_date.py
invidious/enums/sortby.py
invidious/enums/trending.py
invidious/types/__init__.py
invidious/types/channel.py
invidious/types/channel_item.py
invidious/types/channel_playlists.py
invidious/types/comment.py
invidious/types/comments_list.py
invidious/types/model.py
invidious/types/playlist_item.py
invidious/types/recommended_video.py
invidious/types/short_video.py
invidious/types/video.py
invidious/types/video_item.py
invidious.py-0.1.2.dist-info/LICENSE
invidious.py-0.1.2.dist-info/METADATA
invidious.py-0.1.2.dist-info/WHEEL
invidious.py-0.1.2.dist-info/top_level.txt
invidious.py-0.1.2.dist-info/RECORD
