Metadata-Version: 2.1
Name: invidious.py
Version: 0.1.2
Summary: A Python wrapper for Invidious API
Author: loliconshik3
Author-email: loliconshik3@gmail.com
Keywords: python,invidious,youtube,video,api
Classifier: Development Status :: 1 - Planning
Classifier: Intended Audience :: Developers
Classifier: Programming Language :: Python :: 3
Classifier: Operating System :: Unix
Classifier: Operating System :: MacOS :: MacOS X
Classifier: Operating System :: Microsoft :: Windows
License-File: LICENSE
Requires-Dist: requests
Requires-Dist: dataclasses
